Workbook

Sheet Cover
B2: ANALYSE M&A - VALORISATION SFR / ALTICE FRANCE
B4: Point de vue : Consortium Bouygues Telecom / Iliad / Orange
B6: Projet d'études - Valorisation & modélisation financière
B9: Date de l'analyse | C9: Avril 2026
B11: Transaction de référence | C11: Offre consortium ~20 Md€ (jan. 2026)
B13: CA SFR 2024A | C13: 10,0 Md€
B15: EBITDA SFR 2024A | C15: 3,3 Md€
B17: Dette nette post-restructuration | C17: ~15,5 Md€
B19: Méthodes de valorisation | C19: DCF + Multiples comparables
B23: Structure du modèle
B24: 1. Historique | C24: P&L, KPIs opérationnels SFR 2021–2024
B25: 2. Projections | C25: Scénarios Bear / Base / Bull 2025E–2029E
B26: 3. DCF | C26: FCFF, WACC, valeur terminale → Enterprise Value
B27: 4. Multiples | C27: EV/EBITDA sur transactions télécom européennes
B28: 5. Bridge | C28: Enterprise Value → Equity Value
B29: 6. Synthèse | C29: Football field — fourchettes de valorisation
B32: Convention de couleurs
B33: Texte bleu | C33: Hypothèse saisie manuellement (input)
B34: Texte noir | C34: Formule calculée
B35: Texte vert | C35: Lien vers un autre onglet

Sheet A. Sources comptables
B2: ALTICE FRANCE - COMPTES CONSOLIDÉS IFRS (source : rapports officiels) (€m)
B3: Ligne du compte de résultat consolidé | C3: 2022 | D3: 2023 | E3: 2024 | F3: Notes
B4: COMPTE DE RÉSULTAT CONSOLIDÉ
B5: Revenus totaux | C5: 11378.3 | D5: 11144.9 | E5: 10368.4 | F5: Note 6.1 - cf. détail par segment ci-dessous
B6: Résidentiel - Fixe | C6: 2681 | D6: 2608.9 | E6: 2699.9
B7: Résidentiel - Mobile | C7: 3813.8 | D7: 3765.5 | E7: 3603.1
B8: Services Entreprises (B2B + gros) | C8: 3444.4 | D8: 3425 | E8: 2976.1
B9: Ventes d'équipements | C9: 997.6 | D9: 996.8 | E9: 904
B10: Médias (BFMTV/RMC) | C10: 441.5 | D10: 348.6 | E10: 185.4 | F10: Cédé à CMA-CGM en juillet 2024
B11: Achats et sous-traitance | C11: -3427.4 | D11: -3135.9 | E11: -2642.1
B12: Autres charges opérationnelles | C12: -1850.7 | D12: -1889 | E12: -1892.1
B13: Charges de personnel | C13: -1096.9 | D13: -1168.5 | E13: -1174.1
B14: Loyers (IFRS 16 - EBITDAaL) | C14: -1052.8 | D14: -1136.1 | E14: -1231.1 | F14: Loyers opérationnels exclus de l'EBITDA ajusté
B15: EBITDA AJUSTÉ (EBITDAaL) | C15: 3950.2 | D15: 3815.3 | E15: 3429 | F15: Non-GAAP - Note 6.2. Exclut loyers IFRS 16
B16: Marge EBITDA (%) | C16: =C15/C5 -> 0.34716961 | D16: =D15/D5 -> 0.34233596 | E16: =E15/E5 -> 0.33071641 | F16: EBITDA divise par Revenus totaux
B17: Dotations aux amortissements (D&A) | C17: -3384.7 | D17: -3307.7 | E17: -3069.3 | F17: Incl. amort. actifs droits d'utilisation (IFRS 16)
B18: Autres produits et charges | C18: -199.6 | D18: -149.5 | E18: 2777.4 | F18: ⚠ 2024 inclut ~3 Md€ de plus-values cessions actifs
B19: Résultat opérationnel (EBIT) | C19: 1419.1 | D19: 1494.2 | E19: 4368.1 | F19: ⚠ 2024 non comparable -- distorsion plus-values
B20: Coût de l'endettement financier net (RF) | C20: -88 | D20: -2309.4 | E20: -1855.7 | F20: ⚠ 2022 distorsion : +1 107 M€ gains dérivés
B21: Quote-part résultat des sociétés mises en éq. | C21: -135.9 | D21: -158.8 | E21: -54.1
B22: Impôt sur les bénéfices | C22: -352.9 | D22: -129.3 | E22: -483.8
B23: RÉSULTAT NET (part du groupe) | C23: 842.3 | D23: -1103.3 | E23: 1974.5 | F23: ⚠ Distorsions importantes en 2022 et 2024
B25: CAPEX & CASH-FLOWS
B26: Capex accrué (accrual basis) | C26: 2399 | D26: 2325.6 | E26: 2095.1 | F26: Note 6.3 - hors Altice TV/Media
B27: Capex / Revenus (%) | C27: =C26/C5 -> 0.21083993 | D27: =D26/D5 -> 0.20866944 | E27: =E26/E5 -> 0.20206589 | F27: Capex divise par Revenus
B28: OpFCF = EBITDA - Capex | C28: 1551.3 | D28: 1489.7 | E28: 1333.9 | F28: Source : Note 6.4
B29: Variation du BFR (cash-flows) | C29: -131.8 | D29: -335 | E29: 367.7 | F29: Source : tableau des flux de trésorerie
B30: BFR % des revenus | C30: =-C29/C5 -> 0.011583453 | D30: =-D29/D5 -> 0.030058592 | E30: =-E29/E5 -> -0.035463524 | F30: Calculé - très volatile (cf. note)
B31: Trésorerie en fin de période | C31: 368.4 | D31: 451.1 | E31: 2867.1 | F31: ⚠ 2024 : haussse due aux cessions
B32: Dette financière nette | C32: 18958.4 | D32: 20052.2 | E32: 19821.9 | F32: Source : Note 24.4 - hors Altice TV/Participations
B34: ⚠ NOTES IMPORTANTES SUR LES DISTORSIONS COMPTABLES • 2024 - Résultat net & EBIT : inclut +3,0 Md€ de plus-values de cessions (UltraEdge, XpFibre, Altice Media, La Poste Telecom). Non récurrent - à neutraliser dans toute analyse de valorisation. • 2024 - Variation BFR +368 M€ : partiellement liée à l'affacturage inversé (reverse factoring). La variation opérationnelle normalisée est estimée à -100 M€/an en rythme de croisière. • 2022 - Résultat financier quasi nul (-88 M€) : masqué par +1 107 M€ de gains sur dérivés de change. Le coût réel de la dette était ~800 M€/an. • D&A : inclut l'amortissement des actifs droits d'utilisation IFRS 16. L'EBITDAaL (Adjusted EBITDA) déduit les loyers opérationnels, conformément aux standards sectoriels.
B36: Source : Altice France SA -- Comptes consolidés IFRS 2024 (exercice clos le 31/12/2024), 2023 et 2022. Commissaires aux comptes : rapports joints.

Sheet 1. Historique
B2: SFR / ALTICE FRANCE - DONNÉES HISTORIQUES (€m, données auditées)
B3: Indicateur | C3: 2022 | D3: 2023 | E3: 2024 | F3: Source / Note
B4: P&L CONSOLIDÉ SYNTHÉTIQUE
B5: Revenus totaux | C5: ='A. Sources comptables'!C5 -> 11378.3 | D5: ='A. Sources comptables'!D5 -> 11144.9 | E5: ='A. Sources comptables'!E5 -> 10368.4 | F5: → Onglet Sources, ligne Revenus
B6: Résidentiel Fixe + Mobile | C6: ='A. Sources comptables'!C6+'A. Sources comptables'!C7 -> 6494.8 | D6: ='A. Sources comptables'!D6+'A. Sources comptables'!D7 -> 6374.4 | E6: ='A. Sources comptables'!E6+'A. Sources comptables'!E7 -> 6303
B7: B2B / Services Entreprises | C7: ='A. Sources comptables'!C8 -> 3444.4 | D7: ='A. Sources comptables'!D8 -> 3425 | E7: ='A. Sources comptables'!E8 -> 2976.1
B8: Ventes d'équipements | C8: ='A. Sources comptables'!C9 -> 997.6 | D8: ='A. Sources comptables'!D9 -> 996.8 | E8: ='A. Sources comptables'!E9 -> 904
B9: Médias (cédé juil. 2024) | C9: ='A. Sources comptables'!C10 -> 441.5 | D9: ='A. Sources comptables'!D10 -> 348.6 | E9: ='A. Sources comptables'!E10 -> 185.4 | F9: Non récurrent - à exclure des proj.
B10: Croissance des revenus (yoy) | D10: =(D5-C5)/C5 -> -0.02051273 | E10: =(E5-D5)/D5 -> -0.069673124
B11: EBITDA Ajusté (EBITDAaL) | C11: ='A. Sources comptables'!C15 -> 3950.2 | D11: ='A. Sources comptables'!D15 -> 3815.3 | E11: ='A. Sources comptables'!E15 -> 3429 | F11: Non-GAAP - après loyers IFRS 16
B12: Marge EBITDA (%) | C12: =C11/C5 -> 0.34716961 | D12: =D11/D5 -> 0.34233596 | E12: =E11/E5 -> 0.33071641
B13: D&A (amortissements totaux) | C13: ='A. Sources comptables'!C17 -> -3384.7 | D13: ='A. Sources comptables'!D17 -> -3307.7 | E13: ='A. Sources comptables'!E17 -> -3069.3 | F13: Incl. amort. droits d'utilisation IFRS 16
B14: EBIT (résultat opérationnel) | C14: ='A. Sources comptables'!C19 -> 1419.1 | D14: ='A. Sources comptables'!D19 -> 1494.2 | E14: ='A. Sources comptables'!E19 -> 4368.1 | F14: ⚠ 2024 distorsion (plus-values cessions)
B15: dont : autres produits/charges | C15: ='A. Sources comptables'!C18 -> -199.6 | D15: ='A. Sources comptables'!D18 -> -149.5 | E15: ='A. Sources comptables'!E18 -> 2777.4 | F15: ⚠ +2 777 M€ en 2024 = plus-values
B16: Résultat financier net | C16: ='A. Sources comptables'!C20 -> -88 | D16: ='A. Sources comptables'!D20 -> -2309.4 | E16: ='A. Sources comptables'!E20 -> -1855.7 | F16: ⚠ 2022 distordu par gains dérivés
B17: Impôt sur les bénéfices | C17: ='A. Sources comptables'!C22 -> -352.9 | D17: ='A. Sources comptables'!D22 -> -129.3 | E17: ='A. Sources comptables'!E22 -> -483.8
B18: Résultat net (part du groupe) | C18: ='A. Sources comptables'!C23 -> 842.3 | D18: ='A. Sources comptables'!D23 -> -1103.3 | E18: ='A. Sources comptables'!E23 -> 1974.5 | F18: ⚠ Distorsions 2022 et 2024 - cf. notes
B20: CAPEX & FREE CASH-FLOW
B21: Capex accrué | C21: ='A. Sources comptables'!C26 -> 2399 | D21: ='A. Sources comptables'!D26 -> 2325.6 | E21: ='A. Sources comptables'!E26 -> 2095.1 | F21: Note 6.3
B22: Capex / Revenus | C22: =C21/C5 -> 0.21083993 | D22: =D21/D5 -> 0.20866944 | E22: =E21/E5 -> 0.20206589
B23: OpFCF (EBITDA − Capex) | C23: ='A. Sources comptables'!C28 -> 1551.3 | D23: ='A. Sources comptables'!D28 -> 1489.7 | E23: ='A. Sources comptables'!E28 -> 1333.9 | F23: Note 6.4
B24: Variation BFR (flux opérationnels) | C24: ='A. Sources comptables'!C29 -> -131.8 | D24: ='A. Sources comptables'!D29 -> -335 | E24: ='A. Sources comptables'!E29 -> 367.7 | F24: ⚠ Très volatile - cf. notes
B25: BFR % des revenus | C25: =-C24/C5 -> 0.011583453 | D25: =-D24/D5 -> 0.030058592 | E25: =E24/E5 -> 0.035463524
B27: Données issues des comptes consolidés audités Altice France SA. Toutes les cellules vertes renvoient vers l'onglet 'A. Sources comptables'.
B29: 📌 JUSTIFICATION DE L'HYPOTHÈSE BFR POUR LES PROJECTIONS
B30: La variation de BFR est historiquement très volatile chez Altice France : • 2022 : −131,8 M€ (sortie) → BFR = 1,2% des revenus • 2023 : −335,0 M€ (sortie) → BFR = 3,0% des revenus (impact programme départs volontaires) • 2024 : +367,7 M€ (entrée) → trompeuse - liée aux cessions d'actifs et à la réduction de l'affacturage inversé Hypothèse retenue pour les projections : −100 M€/an (≈ 1,0% du CA) = moyenne normalisée sur 3 ans hors éléments exceptionnels. Cette hypothèse est conservatrice (cash outflow modéré) et cohérente avec le profil d'un opérateur télécom en phase de stabilisation. Un opérateur télécom mature a typiquement un BFR négatif stable (abonnés paient à terme échu), la variation est donc structurellement faible.

Sheet 2. Projections
B2: PROJECTIONS FINANCIÈRES 2025E–2029E - 3 SCÉNARIOS (€m)
B3: SENARIOS | D3: ◄ BEAR - Dégradation persistante | J3: BASE - Redressement progressif | P3: BULL - Rebond commercial
D4: 2025E | E4: 2026E | F4: 2027E | G4: 2028E | H4: 2029E | J4: 2025E | K4: 2026E | L4: 2027E | M4: 2028E | N4: 2029E | P4: 2025E | Q4: 2026E | R4: 2027E | S4: 2028E | T4: 2029E
B5: HYPOTHÈSES CLÉS (inputs en bleu - modifiables)
B6: Croissance CA (yoy) | D6: -0.05 | E6: -0.04 | F6: -0.02 | G6: -0.01 | H6: -0.01 | J6: -0.02 | K6: 0 | L6: 0.01 | M6: 0.02 | N6: 0.02 | P6: 0.01 | Q6: 0.02 | R6: 0.03 | S6: 0.03 | T6: 0.03
B7: Marge EBITDA (%) | D7: 0.31 | E7: 0.31 | F7: 0.32 | G7: 0.32 | H7: 0.33 | J7: 0.33 | K7: 0.33 | L7: 0.34 | M7: 0.35 | N7: 0.35 | P7: 0.34 | Q7: 0.35 | R7: 0.36 | S7: 0.37 | T7: 0.38
B8: Capex / CA (%) | D8: 0.21 | E8: 0.21 | F8: 0.2 | G8: 0.2 | H8: 0.2 | J8: 0.2 | K8: 0.2 | L8: 0.19 | M8: 0.19 | N8: 0.18 | P8: 0.19 | Q8: 0.18 | R8: 0.18 | S8: 0.17 | T8: 0.17
B9: Variation BFR (€m) | D9: -100 | E9: -100 | F9: -100 | G9: -100 | H9: -100 | J9: -100 | K9: -100 | L9: -100 | M9: -100 | N9: -100 | P9: -100 | Q9: -100 | R9: -100 | S9: -100 | T9: -100
B10: Taux d'imposition (%) | D10: 0.25 | E10: 0.25 | F10: 0.25 | G10: 0.25 | H10: 0.25 | J10: 0.25 | K10: 0.25 | L10: 0.25 | M10: 0.25 | N10: 0.25 | P10: 0.25 | Q10: 0.25 | R10: 0.25 | S10: 0.25 | T10: 0.25
B12: P&L PROJETÉ ET FCFF
B13: Chiffre d'affaires | D13: ='1. Historique'!E5*(1+D6) -> 9849.98 | E13: =D13*(1+E6) -> 9455.9808 | F13: =E13*(1+F6) -> 9266.8612 | G13: =F13*(1+G6) -> 9174.1926 | H13: =G13*(1+H6) -> 9082.4506 | J13: ='1. Historique'!E5*(1+J6) -> 10161.032 | K13: =J13*(1+K6) -> 10161.032 | L13: =K13*(1+L6) -> 10262.642 | M13: =L13*(1+M6) -> 10467.895 | N13: =M13*(1+N6) -> 10677.253 | P13: ='1. Historique'!E5*(1+P6) -> 10472.084 | Q13: =P13*(1+Q6) -> 10681.526 | R13: =Q13*(1+R6) -> 11001.971 | S13: =R13*(1+S6) -> 11332.031 | T13: =S13*(1+T6) -> 11671.992
B14: Variation CA (€m yoy) | D14: =D13-'1. Historique'!E5 -> -518.42 | E14: =E13-D13 -> -393.9992 | F14: =F13-E13 -> -189.11962 | G14: =G13-F13 -> -92.668612 | H14: =H13-G13 -> -91.741926 | J14: =J13-'1. Historique'!E5 -> -207.368 | K14: =K13-J13 -> 0 | L14: =L13-K13 -> 101.61032 | M14: =M13-L13 -> 205.25285 | N14: =N13-M13 -> 209.3579 | P14: =P13-'1. Historique'!E5 -> 103.684 | Q14: =Q13-P13 -> 209.44168 | R14: =R13-Q13 -> 320.44577 | S14: =S13-R13 -> 330.05914 | T14: =T13-S13 -> 339.96092
B15: EBITDA Ajusté | D15: =D13*D7 -> 3053.4938 | E15: =E13*E7 -> 2931.354 | F15: =F13*F7 -> 2965.3956 | G15: =G13*G7 -> 2935.7416 | H15: =H13*H7 -> 2997.2087 | J15: =J13*J7 -> 3353.1406 | K15: =K13*K7 -> 3353.1406 | L15: =L13*L7 -> 3489.2984 | M15: =M13*M7 -> 3663.7633 | N15: =N13*N7 -> 3737.0386 | P15: =P13*P7 -> 3560.5086 | Q15: =Q13*Q7 -> 3738.534 | R15: =R13*R7 -> 3960.7097 | S15: =S13*S7 -> 4192.8513 | T15: =T13*T7 -> 4435.3568
B16: Marge EBITDA (%) | D16: =D15/D13 -> 0.31 | E16: =E15/E13 -> 0.31 | F16: =F15/F13 -> 0.32 | G16: =G15/G13 -> 0.32 | H16: =H15/H13 -> 0.33 | J16: =J15/J13 -> 0.33 | K16: =K15/K13 -> 0.33 | L16: =L15/L13 -> 0.34 | M16: =M15/M13 -> 0.35 | N16: =N15/N13 -> 0.35 | P16: =P15/P13 -> 0.34 | Q16: =Q15/Q13 -> 0.35 | R16: =R15/R13 -> 0.36 | S16: =S15/S13 -> 0.37 | T16: =T15/T13 -> 0.38
B17: D&A (estimé stable) | D17: ='1. Historique'!E13 -> -3069.3 | E17: =D17 -> -3069.3 | F17: =E17 -> -3069.3 | G17: =F17 -> -3069.3 | H17: =G17 -> -3069.3 | J17: ='1. Historique'!E13 -> -3069.3 | K17: -3069.3 | L17: -3069.3 | M17: -3069.3 | N17: -3069.3 | P17: -3069.3 | Q17: -3069.3 | R17: -3069.3 | S17: -3069.3 | T17: -3069.3
B18: EBIT normalisé | D18: =D15+D17 -> -15.8062 | E18: =E15+E17 -> -137.94595 | F18: =F15+F17 -> -103.90442 | G18: =G15+G17 -> -133.55838 | H18: =H15+H17 -> -72.091287 | J18: =J15+J17 -> 283.84056 | K18: =K15+K17 -> 283.84056 | L18: =L15+L17 -> 419.99839 | M18: =M15+M17 -> 594.46331 | N18: =N15+N17 -> 667.73857 | P18: =P15+P17 -> 491.20856 | Q18: =Q15+Q17 -> 669.23399 | R18: =R15+R17 -> 891.40972 | S18: =S15+S17 -> 1123.5513 | T18: =T15+T17 -> 1366.0568
B19: Capex | D19: =-D13*D8 -> -2068.4958 | E19: =-E13*E8 -> -1985.756 | F19: =-F13*F8 -> -1853.3722 | G19: =-G13*G8 -> -1834.8385 | H19: =-H13*H8 -> -1816.4901 | J19: =-J13*J8 -> -2032.2064 | K19: =-K13*K8 -> -2032.2064 | L19: =-L13*L8 -> -1949.902 | M19: =-M13*M8 -> -1988.9001 | N19: =-N13*N8 -> -1921.9056 | P19: =-P13*P8 -> -1989.696 | Q19: =-Q13*Q8 -> -1922.6746 | R19: =-R13*R8 -> -1980.3549 | S19: =-S13*S8 -> -1926.4452 | T19: =-T13*T8 -> -1984.2386
B20: Capex / CA | D20: =-D19/D13 -> 0.21 | E20: =-E19/E13 -> 0.21 | F20: =-F19/F13 -> 0.2 | G20: =-G19/G13 -> 0.2 | H20: =-H19/H13 -> 0.2 | J20: =-J19/J13 -> 0.2 | K20: =-K19/K13 -> 0.2 | L20: =-L19/L13 -> 0.19 | M20: =-M19/M13 -> 0.19 | N20: =-N19/N13 -> 0.18 | P20: =-P19/P13 -> 0.19 | Q20: =-Q19/Q13 -> 0.18 | R20: =-R19/R13 -> 0.18 | S20: =-S19/S13 -> 0.17 | T20: =-T19/T13 -> 0.17
B21: OpFCF (EBITDA − Capex) | D21: =D15+D19 -> 984.998 | E21: =E15+E19 -> 945.59808 | F21: =F15+F19 -> 1112.0233 | G21: =G15+G19 -> 1100.9031 | H21: =H15+H19 -> 1180.7186 | J21: =J15+J19 -> 1320.9342 | K21: =K15+K19 -> 1320.9342 | L21: =L15+L19 -> 1539.3963 | M21: =M15+M19 -> 1674.8632 | N21: =N15+N19 -> 1815.133 | P21: =P15+P19 -> 1570.8126 | Q21: =Q15+Q19 -> 1815.8594 | R21: =R15+R19 -> 1980.3549 | S21: =S15+S19 -> 2266.4061 | T21: =T15+T19 -> 2451.1182
B22: Variation BFR | D22: =D9 -> -100 | E22: =E9 -> -100 | F22: =F9 -> -100 | G22: =G9 -> -100 | H22: =H9 -> -100 | J22: =J9 -> -100 | K22: =K9 -> -100 | L22: =L9 -> -100 | M22: =M9 -> -100 | N22: =N9 -> -100 | P22: =P9 -> -100 | Q22: =Q9 -> -100 | R22: =R9 -> -100 | S22: =S9 -> -100 | T22: =T9 -> -100
B23: Impôts (sur EBIT × taux IS) | D23: =IF(D18>0,-D18*D10,0) -> 0 | E23: =IF(E18>0,-E18*E10,0) -> 0 | F23: =IF(F18>0,-F18*F10,0) -> 0 | G23: =IF(G18>0,-G18*G10,0) -> 0 | H23: =IF(H18>0,-H18*H10,0) -> 0 | J23: =IF(J18>0,-J18*J10,0) -> -70.96014 | K23: =IF(K18>0,-K18*K10,0) -> -70.96014 | L23: =IF(L18>0,-L18*L10,0) -> -104.9996 | M23: =IF(M18>0,-M18*M10,0) -> -148.61583 | N23: =IF(N18>0,-N18*N10,0) -> -166.93464 | P23: =IF(P18>0,-P18*P10,0) -> -122.80214 | Q23: =IF(Q18>0,-Q18*Q10,0) -> -167.3085 | R23: =IF(R18>0,-R18*R10,0) -> -222.85243 | S23: =IF(S18>0,-S18*S10,0) -> -280.88783 | T23: =IF(T18>0,-T18*T10,0) -> -341.51419
B24: FCFF | D24: =D15+D19+D22+D23 -> 884.998 | E24: =E15+E19+E22+E23 -> 845.59808 | F24: =F15+F19+F22+F23 -> 1012.0233 | G24: =G15+G19+G22+G23 -> 1000.9031 | H24: =H15+H19+H22+H23 -> 1080.7186 | J24: =J15+J19+J22+J23 -> 1149.974 | K24: =K15+K19+K22+K23 -> 1149.974 | L24: =L15+L19+L22+L23 -> 1334.3968 | M24: =M15+M19+M22+M23 -> 1426.2474 | N24: =N15+N19+N22+N23 -> 1548.1984 | P24: =P15+P19+P22+P23 -> 1348.0105 | Q24: =Q15+Q19+Q22+Q23 -> 1548.5509 | R24: =R15+R19+R22+R23 -> 1657.5024 | S24: =S15+S19+S22+S23 -> 1885.5183 | T24: =T15+T19+T22+T23 -> 2009.604
B26: Note méthodologique - FCFF : EBITDA + Capex (négatif) + Variation BFR (sortie cash) + Impôts. D&A maintenu constant à niveau 2024 (hypothèse conservatrice). Pour des projections professionnelles, le D&A devrait décliner proportionnellement au Capex.

Sheet 3. DCF
B2: VALORISATION PAR DCF (€m)
C3: BEAR | D3: BASE | E3: BULL
B4: WACC - COÛT MOYEN PONDÉRÉ DU CAPITAL
B5: Taux sans risque - OAT 10 ans (réf. avr. 2026) | C5: 0.035 | D5: 0.035 | E5: 0.035
B6: Prime de risque marché (ERP) | C6: 0.05 | D6: 0.05 | E6: 0.05
B7: Bêta désendetté - secteur télécom EU | C7: 0.65 | D7: 0.65 | E7: 0.65
B8: Ratio D/(D+E) cible | C8: 0.6 | D8: 0.55 | E8: 0.5
B9: Ratio E/(D+E) cible | C9: =1-C8 -> 0.4 | D9: =1-D8 -> 0.45 | E9: =1-E8 -> 0.5
B10: Bêta ré-endetté (Hamada) | C10: =C7*(1+(C8/C9)*(1-C13)) -> 1.38125 | D10: =D7*(1+(D8/D9)*(1-D13)) -> 1.2458333 | E10: =E7*(1+(E8/E9)*(1-E13)) -> 1.1375
B11: Coût des fonds propres Ke | C11: =C5+C10*C6 -> 0.1040625 | D11: =D5+D10*D6 -> 0.097291667 | E11: =E5+E10*E6 -> 0.091875
B12: Coût de la dette Kd (avant IS) | C12: 0.065 | D12: 0.06 | E12: 0.055
B13: Taux d'imposition | C13: 0.25 | D13: 0.25 | E13: 0.25
B14: Coût de la dette Kd (après IS) | C14: =C12*(1-C13) -> 0.04875 | D14: =D12*(1-D13) -> 0.045 | E14: =E12*(1-E13) -> 0.04125
B15: WACC | C15: =C11*C9+C14*C8 -> 0.070875 | D15: =D11*D9+D14*D8 -> 0.06853125 | E15: =E11*E9+E14*E8 -> 0.0665625
B17: ACTUALISATION DES FCFF (€m)
C18: BEAR | D18: BASE | E18: BULL
B19: 2025E | C19: ='2. Projections'!D24*(1/(1+C15)^1) -> 826.42512 | D19: ='2. Projections'!J24*(1/(1+D15)^1) -> 1076.2194 | E19: ='2. Projections'!P24*(1/(1+E15)^1) -> 1263.8832
B20: 2026E | C20: ='2. Projections'!E24*(1/(1+C15)^2) -> 737.37164 | D20: ='2. Projections'!K24*(1/(1+D15)^2) -> 1007.195 | E20: ='2. Projections'!Q24*(1/(1+E15)^2) -> 1361.2969
B21: 2027E | C21: ='2. Projections'!F24*(1/(1+C15)^3) -> 824.08914 | D21: ='2. Projections'!L24*(1/(1+D15)^3) -> 1093.7632 | E21: ='2. Projections'!R24*(1/(1+E15)^3) -> 1366.1401
B22: 2028E | C22: ='2. Projections'!G24*(1/(1+C15)^4) -> 761.09158 | D22: ='2. Projections'!M24*(1/(1+D15)^4) -> 1094.0721 | E22: ='2. Projections'!S24*(1/(1+E15)^4) -> 1457.0871
B23: 2029E | C23: ='2. Projections'!H24*(1/(1+C15)^5) -> 767.39457 | D23: ='2. Projections'!N24*(1/(1+D15)^5) -> 1111.4514 | E23: ='2. Projections'!T24*(1/(1+E15)^5) -> 1456.0589
B24: Somme FCFF actualisés (2025–2029)
B25: Σ PV(FCFF) | C25: =SUM(C19:C23) -> 3916.372 | D25: =SUM(D19:D23) -> 5382.7011 | E25: =SUM(E19:E23) -> 6904.4662
B27: VALEUR TERMINALE - Gordon-Shapiro
B28: FCFF terminal (2029E) | C28: ='2. Projections'!H24 -> 1080.7186 | D28: ='2. Projections'!N24 -> 1548.1984 | E28: ='2. Projections'!T24 -> 2009.604
B29: Taux de croissance perpétuel (g) | C29: 0.015 | D29: 0.015 | E29: 0.015
B30: WACC (rappel) | C30: =C15 -> 0.070875 | D30: =D15 -> 0.06853125 | E30: =E15 -> 0.0665625
B31: Valeur terminale brute = FCFF×(1+g)/(WACC−g) | C31: =C28*(1+C29)/(C30-C29) -> 19631.845 | D31: =D28*(1+D29)/(D30-D29) -> 29355.215 | E31: =E28*(1+E29)/(E30-E29) -> 39558.751
B32: Facteur d'actualisation (1/(1+WACC)^n) | C32: =1/(1+C30)^COUNTA(B19:B23) -> 0.71007807 | D32: =1/(1+D30)^COUNTA(C19:C23) -> 0.71789985 | E32: =1/(1+E30)^COUNTA(D19:D23) -> 0.72455015
B33: Valeur terminale actualisée | C33: =C31*C32 -> 13940.143 | D33: =D31*D32 -> 21074.104 | E33: =E31*E32 -> 28662.299
B35: ENTERPRISE VALUE (DCF)
B36: Σ PV(FCFF) 2025–2029 | C36: =C25 -> 3916.372 | D36: =D25 -> 5382.7011 | E36: =E25 -> 6904.4662
B37: Valeur terminale actualisée | C37: =C33 -> 13940.143 | D37: =D33 -> 21074.104 | E37: =E33 -> 28662.299
B38: ENTERPRISE VALUE (DCF) | C38: =C36+C37 -> 17856.515 | D38: =D36+D37 -> 26456.805 | E38: =E36+E37 -> 35566.765
B39: EV/EBITDA 2024 implicite | C39: =C38/3429 -> 5.2074993 | D39: =D38/3429 -> 7.7156038 | E39: =E38/3429 -> 10.372343
B40: % représenté par la valeur terminale | C40: =C37/C38 -> 0.78067545 | D40: =D37/D38 -> 0.79654758 | E40: =E37/E38 -> 0.80587309
B42: Note DCF : WACC : Bêta ré-endetté calculé via formule Hamada -- β_L = β_U × [1 + D/E × (1−t)]. Taux sans risque = OAT 10 ans avril 2026 (≈3,3%). ERP = 5,5% (source Damodaran). g = 1,5% = taux de croissance nominale long terme du secteur télécom européen. Valeur terminale brute calculé via la méthode Gordon-Shapiro = FCFF×(1+g)/(WACC−g) ⚠ La valeur terminale représente souvent 70-80% de l'EV - les hypothèses de WACC et g sont donc critiques.

Sheet 4. Multiples
B2: VALORISATION PAR LES MULTIPLES - TRANSACTIONS COMPARABLES (€m)
B3: Transaction | C3: Année | D3: EV (€m) | E3: CA (€m) | F3: EBITDA (€m) | G3: EV/EBITDA | H3: Source / Note
B4: TRANSACTIONS TÉLÉCOM EUROPÉENNES RÉCENTES
B5: Vodafone UK / Three UK (fusion) | C5: 2024 | D5: 15000 | E5: 5800 | F5: 1850 | G5: =D5/F5 -> 8.1081081 | H5: Financial Times, déc. 2024
B6: Orange / MásMóvil - JV Espagne | C6: 2023 | D6: 18600 | E6: 6700 | F6: 2200 | G6: =D6/F6 -> 8.4545455 | H6: Communiqué Orange, mars 2023
B7: Proximus / BICS - acquisition | C7: 2023 | D7: 1150 | E7: 420 | F7: 130 | G7: =D7/F7 -> 8.8461538 | H7: Proximus IR, 2023
B8: Deutsche Telekom / GD Towers (cession) | C8: 2022 | D8: 17500 | E8: 620 | F8: 430 | G8: =D8/F8 -> 40.697674 | H8: Bloomberg, 2022
B9: Iliad / Play (Pologne) | C9: 2020 | D9: 4000 | E9: 1050 | F9: 340 | G9: =D9/F9 -> 11.764706 | H9: Communiqué Iliad, 2020
B10: Altice / SFR (acquisition par Drahi) | C10: 2014 | D10: 17000 | E10: 10600 | F10: 3600 | G10: =D10/F10 -> 4.7222222 | H10: Réf. historique - base de comparaison
B11: ⚠ Ligne 2014 (Drahi/SFR) = référence historique - exclue des statistiques car non comparable au marché actuel
B13: STATISTIQUES (hors transaction 2014)
B14: Multiple médian | C14: =MEDIAN(G5:G9) -> 8.8461538
B15: Multiple moyen | C15: =AVERAGE(G5:G9) -> 15.574238
B16: Quartile 25 (plancher) | C16: =QUARTILE(G5:G9,1) -> 8.4545455
B17: Quartile 75 (plafond) | C17: =QUARTILE(G5:G9,3) -> 11.764706
B19: APPLICATION À SFR (EBITDA 2024 ajusté = 3 429 €m)
B20: Scénario | C20: Multiple | D20: EV calculée (€m) | H20: Commentaire
B21: Bear - plancher (Q1) | C21: =C16 -> 8.4545455 | D21: =C21*3429 -> 28990.636 | H21: Multiple bas - dégradation commerciale
B22: Central - médiane | C22: =C14 -> 8.8461538 | D22: =C22*3429 -> 30333.462 | H22: Référence centrale
B23: Bull - plafond (Q3) | C23: =C17 -> 11.764706 | D23: =C23*3429 -> 40341.176 | H23: Multiple haut - redressement confirmé
B24: Offre consortium (jan. 2026) | C24: =20000/3429 -> 5.8326043 | D24: =C24*3429 -> 20000 | H24: ~20 Md€ / 3 429 M€ EBITDA
B25: Seuil créanciers (7x EBITDA) | C25: 7 | D25: =C25*3429 -> 24003 | H25: Condition veto CA du conseil

Sheet 5. Bridge EV→Equity
B2: BRIDGE ENTERPRISE VALUE → EQUITY VALUE (€m)
C3: BEAR | D3: BASE | E3: BULL | F3: Note
B4: A. ENTERPRISE VALUE RETENUE
B5: EV DCF (onglet 3) | C5: ='3. DCF'!C38 -> 17856.515 | D5: ='3. DCF'!D38 -> 26456.805 | E5: ='3. DCF'!E38 -> 35566.765 | F5: Lien direct vers DCF
B6: EV Multiples - médiane | C6: ='4. Multiples'!D22 -> 30333.462 | D6: ='4. Multiples'!D22 -> 30333.462 | E6: ='4. Multiples'!D22 -> 30333.462 | F6: Multiple médian × EBITDA 2024A
B7: EV retenue (moy. DCF + Multiples) | C7: =AVERAGE(C5,C6) -> 24094.988 | D7: =AVERAGE(D5,D6) -> 28395.133 | E7: =AVERAGE(E5,E6) -> 32950.113 | F7: Fourchette centrale retenue
B8: EV/EBITDA 2024 implicite | C8: =C7/'1. Historique'!$E$11 -> 7.0268266 | D8: =D7/'1. Historique'!$E$11 -> 8.2808788 | E8: =E7/'1. Historique'!$E$11 -> 9.6092485
B10: B. DÉDUCTIONS - DETTE & AJUSTEMENTS (données sources : Note 24.4)
B11: (−) Dette financière nette (post-restructuration oct. 2025) | C11: -15500 | D11: -15500 | E11: -15500 | F11: Source : après plan sauvegarde - environ 15,5 Md€
B12: (−) Obligations locatives (IFRS 16 - hors EBITDA) | C12: -3200 | D12: -3200 | E12: -3200 | F12: Estimé d'après niveau loyers × 2,6x - à affiner DD
B13: (−) Provisions & engagements hors-bilan (est.) | C13: -500 | D13: -500 | E13: -500 | F13: Estimé - retraites, litiges, garanties
B14: (−) Intérêts minoritaires | C14: -150 | D14: -150 | E14: -150 | F14: Source comptes consolidés - NCI faibles
B15: (+) Trésorerie & équivalents (réel 31/12/2024) | C15: ='A. Sources comptables'!$E$31 -> 2867.1 | D15: ='A. Sources comptables'!$E$31 -> 2867.1 | E15: ='A. Sources comptables'!$E$31 -> 2867.1 | F15: Source : Note 24.4 - 2 867 M€
B16: Total ajustements (dette nette élargie) | C16: =SUM(C11:C15) -> -16482.9 | D16: =SUM(D11:D15) -> -16482.9 | E16: =SUM(E11:E15) -> -16482.9
B18: C. EQUITY VALUE
B19: EQUITY VALUE = EV + Ajustements | C19: =C7+C16 -> 7612.0882 | D19: =D7+D16 -> 11912.233 | E19: =E7+E16 -> 16467.213
B21: D. ANALYSE DE L'OFFRE DU CONSORTIUM
B22: Offre actuelle consortium (~jan. 2026) | C22: 20000 | D22: 20000 | E22: 20000 | F22: Dette incluse - source presse/BFM Business
B23: Seuil créanciers - veto à moins de 7x EBITDA | C23: 23003 | D23: 23003 | E23: 23003 | F23: 7 x 3 429 M euros EBITDA 2024A
B24: Prime / (Décote) de l'offre vs EV retenue | C24: =(C22-C7)/C7 -> -0.16995187 | D24: =(C22-D7)/D7 -> -0.29565395 | E24: =(C22-E7)/E7 -> -0.39302181 | F24: Offre moins EV retenue divise par EV retenue
B25: EV/EBITDA 2024 implicite de l'offre | C25: =C22/'1. Historique'!$E$11 -> 5.8326043 | D25: =D22/'1. Historique'!$E$11 -> 5.8326043 | E25: =E22/'1. Historique'!$E$11 -> 5.8326043 | F25: Offre divise par 3 429 M euros EBITDA
B26: Upside nécessaire pour atteindre seuil créanciers | C26: =(C23-C22)/C22 -> 0.15015 | D26: =(C23-C22)/C22 -> 0.15015 | E26: =(C23-C22)/C22 -> 0.15015 | F26: Seuil moins Offre divise par Offre
B28: Note dettes : La dette financière nette post-restructuration (oct. 2025) est estimée à ~15,5 Md€ (Altice France post plan sauvegarde). Les obligations locatives IFRS 16 (~3,2 Md€ estimé) ne sont pas dans la dette nette stricte mais représentent un engagement réel. À affiner via due diligence. La trésorerie de 2 867 M€ inclut des cash issus des cessions 2024 - partiellement affectée au désendettement.

Sheet 6. Synthèse
B2: SYNTHÈSE - FOOTBALL FIELD (Enterprise Value, €m)
B3: Méthode | C3: BEAR | D3: BASE | E3: BULL | F3: Commentaire
B4: RÉCAPITULATIF DES VALORISATIONS EV
B5: DCF (WACC scénarisé) | C5: ='3. DCF'!C38 -> 17856.515 | D5: ='3. DCF'!D38 -> 26456.805 | E5: ='3. DCF'!E38 -> 35566.765 | F5: Très sensible au WACC et à la valeur terminale
B6: Multiples EV/EBITDA (Q1–Q3) | C6: ='4. Multiples'!D21 -> 28990.636 | D6: ='4. Multiples'!D22 -> 30333.462 | E6: ='4. Multiples'!D23 -> 40341.176 | F6: Basé sur 5 transactions télécom EU récentes
B7: EV centrale retenue (moy.) | C7: ='5. Bridge EV→Equity'!C7 -> 24094.988 | D7: ='5. Bridge EV→Equity'!D7 -> 28395.133 | E7: ='5. Bridge EV→Equity'!E7 -> 32950.113 | F7: Fourchette de valorisation stand-alone
B8: Offre consortium (jan. 2026) | C8: ='5. Bridge EV→Equity'!C22 -> 20000 | D8: ='5. Bridge EV→Equity'!D22 -> 20000 | E8: ='5. Bridge EV→Equity'!E22 -> 20000 | F8: Offre révisée ~20 Md€ - due dil. en cours
B9: Seuil créanciers - veto | C9: ='5. Bridge EV→Equity'!C23 -> 23003 | D9: ='5. Bridge EV→Equity'!D23 -> 23003 | E9: ='5. Bridge EV→Equity'!E23 -> 23003 | F9: 7× EBITDA 2024A = 23,0 Md€
B12: ANALYSE SYNTHÉTIQUE DE L'OFFRE
B13: EV/EBITDA implicite offre (20 Md€) | C13: ='5. Bridge EV→Equity'!C22/'1. Historique'!E11 -> 5.8326043 | F13: Versus médiane transactions ~6–7x
B14: Prime / (décote) vs EV centrale Bear | C14: =('5. Bridge EV→Equity'!C22-'3. DCF'!C38)/'3. DCF'!C38 -> 0.12003938
B15: Prime / (décote) vs EV centrale Base | C15: =('5. Bridge EV→Equity'!C22-'3. DCF'!D38)/'3. DCF'!D38 -> -0.24405083
B16: Prime / (décote) vs EV centrale Bull | C16: =('5. Bridge EV→Equity'!C22-'3. DCF'!E38)/'3. DCF'!E38 -> -0.43767728
B17: Gap avec seuil créanciers (23,0 Md€) | C17: ='5. Bridge EV→Equity'!C23-'5. Bridge EV→Equity'!C22 -> 3003 | F17: M€ à combler dans la négociation
B20: RISQUES & POINTS DE VIGILANCE POUR L'ACQUÉREUR
B21: ⚠ Antitrust : Le régulateur ne rendra pas de décision avant fin 2026/début 2027 selon l'Autorité de la concurrence. Risque de blocage ou de remèdes coûteux (cession d'actifs, MVNO imposé).
B22: ⚠ Attrition abonnés : SFR a perdu >1,5M abonnés mobiles en 2 ans. La stabilisation (plan SFR Imagine) est une hypothèse centrale mais non garantie. Le scénario Bear assume une poursuite du déclin.
B23: ⚠ Synergies non modélisées : L'onglet actuel valorise SFR en standalone. Les synergies (réseau, SI, RH, achats) pour Bouygues/Free/Orange pourraient ajouter 1–3 Md€ de valeur actualisée - à modéliser séparément.
B24: ⚠ Exécution post-closing : Intégration d'un acteur avec 25M clients, 30k salariés, ~30 Md€ de dette résiduelle. Risque opérationnel majeur de migration des clients et des systèmes.
B25: ⚠ Dette résiduelle : 15,5 Md€ de dette + ~3,2 Md€ de leasing IFRS 16. Le service de la dette absorbera l'essentiel des FCF des premières années post-acquisition.
B26: ⚠ Régulation des fréquences 5G : Renouvellement de licences à anticiper - impact capex significatif non inclus dans les projections actuelles.
B28: Source des données : Altice France SA - comptes consolidés audités 2022, 2023, 2024. Comparables : presse financière, Bloomberg. Modèle construit à des fins pédagogiques.

Sheet Word
B2: Hypothèses Bear | C2: 25E | D2: 26E | E2: 27E | F2: 28E | G2: 29E
B3: Croissance CA (yoy) | C3: -0.05 | D3: -0.04 | E3: -0.02 | F3: -0.01 | G3: -0.01
B4: Marge EBITDA (%) | C4: 0.31 | D4: 0.31 | E4: 0.32 | F4: 0.32 | G4: 0.33
B5: Capex / CA (%) | C5: 0.21 | D5: 0.21 | E5: 0.2 | F5: 0.2 | G5: 0.2
B8: Hypothèses Base | C8: 25E | D8: 26E | E8: 27E | F8: 28E | G8: 29E
B9: Croissance CA (yoy) | C9: -0.02 | D9: 0 | E9: 0.01 | F9: 0.02 | G9: 0.02
B10: Marge EBITDA (%) | C10: 0.33 | D10: 0.33 | E10: 0.34 | F10: 0.35 | G10: 0.35
B11: Capex / CA (%) | C11: 0.2 | D11: 0.2 | E11: 0.19 | F11: 0.19 | G11: 0.18
B14: Hypothèses Bull | C14: 25E | D14: 26E | E14: 27E | F14: 28E | G14: 29E
B15: Croissance CA (yoy) | C15: 0.01 | D15: 0.02 | E15: 0.03 | F15: 0.03 | G15: 0.03
B16: Marge EBITDA (%) | C16: 0.34 | D16: 0.35 | E16: 0.36 | F16: 0.37 | G16: 0.38
B17: Capex / CA (%) | C17: 0.19 | D17: 0.18 | E17: 0.18 | F17: 0.17 | G17: 0.17
